LICENSE
MANIFEST.in
README.md
requirements.txt
setup.py
tests/__init__.py
tests/dnadiff_test.py
tests/edit_distance_test.py
tests/probe_mapping_test.py
tests/probe_test.py
tests/recall_test.py
tests/tasks_test.py
tests/truth_variant_finding_test.py
tests/utils_test.py
tests/vcf_evaluate_test.py
tests/vcf_stats_test.py
varifier/__init__.py
varifier/__main__.py
varifier/dnadiff.py
varifier/edit_distance.py
varifier/probe.py
varifier/probe_mapping.py
varifier/recall.py
varifier/truth_variant_finding.py
varifier/utils.py
varifier/vcf_evaluate.py
varifier/vcf_stats.py
varifier.egg-info/PKG-INFO
varifier.egg-info/SOURCES.txt
varifier.egg-info/dependency_links.txt
varifier.egg-info/entry_points.txt
varifier.egg-info/requires.txt
varifier.egg-info/top_level.txt
varifier/tasks/__init__.py
varifier/tasks/make_truth_vcf.py
varifier/tasks/vcf_eval.py