Metadata-Version: 1.1
Name: varifier
Version: 0.3.1
Summary: varifier: variant call verification
Home-page: https://github.com/iqbal-lab-org/varifier
Author: Martin Hunt
Author-email: mhunt@ebi.ac.uk
License: MIT
Platform: UNKNOWN
Classifier: Development Status :: 4 - Beta
Classifier: Topic :: Scientific/Engineering :: Bio-Informatics
Classifier: Programming Language :: Python :: 3 :: Only
Classifier: License :: OSI Approved :: MIT License
